phpipam_api/__init__.py
phpipam_api/backend.py
phpipam_api/resources.py
phpipam_api-1.1.0.dist-info/LICENSE
phpipam_api-1.1.0.dist-info/METADATA
phpipam_api-1.1.0.dist-info/WHEEL
phpipam_api-1.1.0.dist-info/top_level.txt
phpipam_api-1.1.0.dist-info/RECORD
