Metadata-Version: 2.1
Name: phpipam-api
Version: 1.1.0
Summary: phpIPAM API implementation
Home-page: https://github.com/kompetenzbolzen/python-phpipam
Author: Jonas Gunz
Author-email: himself@jonasgunz.de
License: MIT
Classifier: Programming Language :: Python :: 3
Classifier: License :: OSI Approved :: MIT License
Classifier: Operating System :: OS Independent
License-File: LICENSE
Requires-Dist: requests (>=2.25.1)
Requires-Dist: python-dateutil (>=2.8.1)
